{
	"id": "withings",
	"name": "Withings",
	"pluginVersion": "1.0.0",
	"description": {
		"fr_FR": "Plugin pour récupérer les données de santé depuis les balances Withings (poids, IMC, masse musculaire, masse grasse, etc.)",
		"en_US": "Plugin to retrieve health data from Withings scales (weight, BMI, muscle mass, fat mass, etc.)"
	},
	"licence": "AGPL",
	"author": "Jeedom Community",
	"require": "4.2",
	"os": {
		"min": 10,
		"max": 12.99
	},
	"category": "health",
	"hasDependency": false,
	"hasOwnDeamon": false,
	"changelog_beta": "https://doc.jeedom.com/#language#/plugins/health/withings/beta/changelog",
	"changelog": "https://doc.jeedom.com/#language#/plugins/health/withings/changelog",
	"documentation_beta": "https://doc.jeedom.com/#language#/plugins/health/withings/beta",
	"documentation": "https://doc.jeedom.com/#language#/plugins/health/withings",
	"link": {
		"forum": "Lien vers le forum Jeedom",
		"video": "Lien vers une vidéo de présentation"
	},
	"language": [
		"fr_FR",
		"en_US"
	],
	"compatibility": [
		"smart",
		"luna",
		"atlas",
		"rpi",
		"docker",
		"diy",
		"mobile"
	]
}
